reddit2epub/__init__.py
reddit2epub/reddit2epubCli.py
reddit2epub/reddit2epubLib.py
reddit2epub-0.5.0.dist-info/LICENSE
reddit2epub-0.5.0.dist-info/METADATA
reddit2epub-0.5.0.dist-info/WHEEL
reddit2epub-0.5.0.dist-info/entry_points.txt
reddit2epub-0.5.0.dist-info/top_level.txt
reddit2epub-0.5.0.dist-info/RECORD
