Metadata-Version: 2.1
Name: reddit2epub
Version: 0.5.0
Summary: A CLI to convert reddit series into epub files
Home-page: https://github.com/mircohaug/reddit2epub.git
Author: Mirco Haug
Author-email: python@mircohaug.de
License: UNKNOWN
Platform: UNKNOWN
Classifier: Development Status :: 4 - Beta
Classifier: Environment :: Console
Classifier: Intended Audience :: End Users/Desktop
Classifier: Programming Language :: Python :: 3
Classifier: License :: OSI Approved :: GNU General Public License v3 (GPLv3)
Classifier: Topic :: Utilities
Requires-Dist: click (==7.*)
Requires-Dist: praw (==6.*)
Requires-Dist: EbookLib (==0.17.*)
